warpseq/__init__.py
warpseq/version.py
warpseq/api/__init__.py
warpseq/api/callbacks.py
warpseq/api/demo.py
warpseq/api/exceptions.py
warpseq/api/public.py
warpseq/api/interfaces/__init__.py
warpseq/api/interfaces/base.py
warpseq/api/interfaces/clips.py
warpseq/api/interfaces/data_pools.py
warpseq/api/interfaces/devices.py
warpseq/api/interfaces/instruments.py
warpseq/api/interfaces/patterns.py
warpseq/api/interfaces/player.py
warpseq/api/interfaces/scales.py
warpseq/api/interfaces/scenes.py
warpseq/api/interfaces/song.py
warpseq/api/interfaces/tracks.py
warpseq/api/interfaces/transforms.py
warpseq/model/__init__.py
warpseq/model/base.py
warpseq/model/chord.py
warpseq/model/clip.py
warpseq/model/context.py
warpseq/model/data_pool.py
warpseq/model/device.py
warpseq/model/directions.py
warpseq/model/evaluator.py
warpseq/model/event.py
warpseq/model/instrument.py
warpseq/model/note.py
warpseq/model/note_table.py
warpseq/model/pattern.py
warpseq/model/registers.py
warpseq/model/scale.py
warpseq/model/scene.py
warpseq/model/slot.py
warpseq/model/song.py
warpseq/model/status.py
warpseq/model/track.py
warpseq/model/transform.py
warpseq/pages/__init__.py
warpseq/pages/base.py
warpseq/pages/clip.py
warpseq/pages/data_pool.py
warpseq/pages/device.py
warpseq/pages/instrument.py
warpseq/pages/pattern.py
warpseq/pages/scale.py
warpseq/pages/scene.py
warpseq/pages/song.py
warpseq/pages/track.py
warpseq/pages/transform.py
warpseq/parser/__init__.py
warpseq/parser/data_slots.py
warpseq/parser/web_slots.py
warpseq/playback/__init__.py
warpseq/playback/midi.py
warpseq/playback/multi_player.py
warpseq/playback/player.py
warpseq/playback/realtime_engine.py
warpseq/server/__init__.py
warpseq/server/callbacks.py
warpseq/server/engine.py
warpseq/server/model_router.py
warpseq/server/packet.py
warpseq/server/page_builder.py
warpseq/server/templar.py
warpseq/server/web_server.py
warpseq/server/widgets.py
warpseq/static/.DS_Store
warpseq/static/ag-grid-community.min.js
warpseq-1.1.1.dist-info/LICENSE
warpseq-1.1.1.dist-info/METADATA
warpseq-1.1.1.dist-info/NOTICE
warpseq-1.1.1.dist-info/WHEEL
warpseq-1.1.1.dist-info/top_level.txt
warpseq-1.1.1.dist-info/RECORD
